sepsis/__init__.py
sepsis-0.0.4.dist-info/METADATA
sepsis-0.0.4.dist-info/WHEEL
sepsis-0.0.4.dist-info/top_level.txt
sepsis-0.0.4.dist-info/RECORD
