Metadata-Version: 2.1
Name: sepsis
Version: 0.0.4
Summary: Module for sepsis predictions
Home-page: https://github.com/sslavian812/sepsis-predictions.git
Author: @Margo78, @akp1n
Author-email: timtimk30@yandex.ru
License: UNKNOWN
Keywords: example python
Platform: UNKNOWN
Classifier: Programming Language :: Python :: 3.11
Classifier: License :: OSI Approved :: MIT License
Classifier: Operating System :: OS Independent
Requires-Python: >=3.7
Requires-Dist: requests (>=2.25.1)
